{
  "@context": [
    "https://w3id.org/ro/crate/1.2/context",
    {
      "bia": "https://bioimage-archive.org/ro-crate/",
      "obo": "http://purl.obolibrary.org/obo/",
      "dwc": "http://rs.tdwg.org/dwc/terms/",
      "dwciri": "http://rs.tdwg.org/dwc/iri/",
      "bao": "http://www.bioassayontology.org/bao#",
      "xsd": "http://www.w3.org/2001/XMLSchema#",
      "vernacularName": {
        "@id": "dwc:vernacularName"
      },
      "scientificName": {
        "@id": "dwc:scientificName"
      },
      "hasCellLine": {
        "@id": "bao:BAO_0002004"
      },
      "measurementMethod": {
        "@id": "dwciri:measurementMethod"
      },
      "seeAlso": {
        "@id": "rdf:seeAlso"
      },
      "BioSample": {
        "@id": "http://schema.org/BioSample"
      },
      "LabProtocol": {
        "@id": "http://schema.org/LabProtocol"
      },
      "labEquipment": {
        "@id": "http://schema.org/labEquipment"
      }
    }
  ],
  "@graph": [
    {
      "@id": "ro-crate-metadata.json",
      "@type": "CreativeWork",
      "conformsTo": {
        "@id": "https://w3id.org/ro/crate/1.2"
      },
      "about": {
        "@id": "https://www.ebi.ac.uk/biostudies/bioimages/studies/S-BIAD2269"
      }
    },
    {
      "@id": "https://www.ebi.ac.uk/biostudies/bioimages/studies/S-BIAD2269",
      "@type": [
        "Dataset"
      ],
      "measurementMethod": [
        {
          "@id": "#1af24027-4b94-438d-bc58-e50b181850da"
        },
        {
          "@id": "#9577880a-4453-4b3b-aa04-d634402f7b5e"
        },
        {
          "@id": "#da9051d5-3650-4be7-8688-f04878bd744b"
        },
        {
          "@id": "#745d90ad-58a1-4403-869c-1bdf3ab2a936"
        },
        {
          "@id": "#ab4ad2a2-2c88-46a5-9d79-a3d0ff9b4081"
        },
        {
          "@id": "#4c2bd05d-fff9-4056-8e7b-165168a9c58b"
        },
        {
          "@id": "#0f8c3557-01a7-4dce-95ea-02df11ef2759"
        },
        {
          "@id": "#e7da1cca-af16-4456-b2b3-1565276c197d"
        },
        {
          "@id": "#4e1ef450-863d-4cd6-a14a-f513bc9bb5ed"
        },
        {
          "@id": "#b1655cb1-974e-4f78-b689-6cc91e1561d8"
        },
        {
          "@id": "#c8886441-6f0a-4b76-8838-4e023355ca75"
        },
        {
          "@id": "#7cdea816-f5ed-4b28-bb7e-69496fa75530"
        },
        {
          "@id": "obo:FBbi_00000253"
        }
      ],
      "about": [
        {
          "@id": "#09e42620-efac-40fe-9371-ea1ab09d4565"
        },
        {
          "@id": "#16412a93-a529-40c5-8a4d-2d9917224f17"
        },
        {
          "@id": "#53a56d78-8a97-4a32-991d-4e34598853c5"
        },
        {
          "@id": "#0901deee-337e-4c2b-b8d1-86c313ab4dd0"
        },
        {
          "@id": "#0f4d703f-0712-4c78-9626-a1746c9fc973"
        },
        {
          "@id": "#82d54a62-228d-4777-9c03-edb252ae232d"
        },
        {
          "@id": "#dc1955f8-e10f-4573-9c9f-2c174168663c"
        },
        {
          "@id": "#435ebc27-6a1c-46d1-a604-e0bdc02eed2c"
        },
        {
          "@id": "#f500750a-7c33-4ade-9d40-acb6a342c44f"
        },
        {
          "@id": "#b87a756e-1614-42ca-ac3c-b9fec3827151"
        },
        {
          "@id": "#fa56d995-c1ba-4bfc-99f4-b1c9d120ca74"
        },
        {
          "@id": "#2e202e92-1a87-4d67-8f74-de79ddce334a"
        },
        {
          "@id": "obo:NCBITaxon_4577"
        },
        {
          "@id": "obo:NCBITaxon_9606"
        },
        {
          "@id": "obo:NCBITaxon_5270"
        },
        {
          "@id": "obo:NCBITaxon_51208"
        },
        {
          "@id": "obo:NCBITaxon_78475"
        },
        {
          "@id": "obo:NCBITaxon_4513"
        }
      ],
      "author": [
        {
          "@id": "https://orcid.org/0000-0003-1717-3138"
        },
        {
          "@id": "https://orcid.org/0000-0003-3054-3121"
        },
        {
          "@id": "https://orcid.org/0000-0002-1438-4389"
        },
        {
          "@id": "https://orcid.org/0000-0001-5805-5774"
        },
        {
          "@id": "https://orcid.org/0009-0000-1254-7431"
        },
        {
          "@id": "https://orcid.org/0000-0003-2292-9286"
        },
        {
          "@id": "https://orcid.org/0000-0001-9301-3211"
        },
        {
          "@id": "#edb39b9b-aa8f-4a56-ab9b-6202aa2c9066"
        },
        {
          "@id": "https://orcid.org/0000-0002-3409-2340"
        },
        {
          "@id": "https://orcid.org/0000-0002-3844-9933"
        },
        {
          "@id": "https://orcid.org/0000-0002-3562-6121"
        },
        {
          "@id": "https://orcid.org/0000-0002-7059-4030"
        },
        {
          "@id": "https://orcid.org/0000-0001-9951-9395"
        },
        {
          "@id": "https://orcid.org/0000-0002-8773-8862"
        },
        {
          "@id": "https://orcid.org/0000-0001-7411-9299"
        },
        {
          "@id": "https://orcid.org/0009-0002-1414-3291"
        },
        {
          "@id": "https://orcid.org/0000-0002-7122-2343"
        },
        {
          "@id": "https://orcid.org/0000-0002-7986-1158"
        },
        {
          "@id": "https://orcid.org/0000-0003-0536-835X"
        },
        {
          "@id": "https://orcid.org/0009-0002-4195-2406"
        },
        {
          "@id": "https://orcid.org/0009-0009-2532-9121"
        },
        {
          "@id": "https://orcid.org/0009-0004-6533-7410"
        },
        {
          "@id": "https://orcid.org/0000-0002-6209-2364"
        },
        {
          "@id": "https://orcid.org/0000-0002-6300-5541"
        },
        {
          "@id": "https://orcid.org/0009-0001-9020-1169"
        },
        {
          "@id": "https://orcid.org/0000-0001-9309-7531"
        },
        {
          "@id": "#7ade1c84-0681-44ef-8c91-be9d0c6ffea5"
        },
        {
          "@id": "#d254d791-cd79-4da9-98dc-a91c15a28d18"
        },
        {
          "@id": "https://orcid.org/0000-0002-9845-6393"
        },
        {
          "@id": "https://orcid.org/0000-0002-3706-7458"
        },
        {
          "@id": "#a94f0486-8903-40bf-8d71-f772285003b5"
        },
        {
          "@id": "https://orcid.org/0009-0000-0645-6891"
        },
        {
          "@id": "#bf52a493-dfb2-489e-90b8-fcc88494e54e"
        },
        {
          "@id": "https://orcid.org/0000-0001-5160-6342"
        },
        {
          "@id": "https://orcid.org/0000-0002-5782-9085"
        }
      ],
      "citation": [
        {
          "@id": "https://doi.org/10.1186/s13059-025-03624-4"
        },
        {
          "@id": "https://doi.org/10.3389/fmars.2017.00083"
        },
        {
          "@id": "https://doi.org/10.1186/s12983-022-00478-5"
        },
        {
          "@id": "https://doi.org/10.3389/fmars.2021.760036"
        },
        {
          "@id": "https://doi.org/10.5281/zenodo.15421751"
        },
        {
          "@id": "https://doi.org/10.1101/2024.07.04.602038"
        }
      ],
      "datePublished": "2025-09-15",
      "description": "Our calendar goes into a second round!\nAfter having a first edition of the NFDI4BIOIMAGE calendar in 2024, we were eager to assemble an improved version for 2025. This time, we invited also other consortia of the National Research Data Infrastructure (NFDI) to contribute with the aim to extend our calendar to a consortium spanning edition. In this year’s calendar we present very different types of images, taken by mobile phones, cameras, drones, and microscopes, representing the work of our colleagues from the various consortia of NFDI.\n\nAs you may know, biological images often include additional information in the form of technical metadata, detailing the conditions under which the image was captured. Ideally, this technical data is paired with biological metadata, which explains the specimen depicted and how it was prepared. This year, we also requested that authors submit their images with complete accompanying metadata – a \"full package\". In bioimaging, the use of metadata standards, specifically the Recommended Metadata for Biological Images (REMBI) guideline (https://doi.org/10.1038/s41592-021-01166-8), has become increasingly common. Many of the submissions for this calendar adhere to REMBI guidelines with comprehensive metadata annotations alongside the bioimage data, as you can observe on the right accompanying our cover image.\n\nHowever, for images captured with other tools, such as mobile phones or drones – images not typically classified as biological – the required metadata differs to accurately convey what is shown and why the image was created. Through this calendar, we step outside the bioimaging sphere to explore how metadata for other types of images might be structured.\n\nWe hope you will find it as exciting as we do to see all the different contributions and the plethora of information that will teach you more about the respective images.\n\nNFDI4BIOMAGE – who we are and what we are aiming for\nThe NFDI4BIOIMAGE consortium started its work in March 2023 as one of the third round applicants within the NFDI, funded by the Federal Ministry for Education and Research (BMBF) and the Länder. Our consortium is working on solutions for bioimage data management along the bioimage life cycle.\n\nBioimaging is an indispensable tool within life and medical sciences. But bioimaging data is also a very divers type of data that is present in numerous proprietary file types, is usually of large size and covers many different imaging modalities. Due to this heterogeneity, storage and interaction with bioimaging data is not trivial and is handled very differently within the research community. Our aim is to find solutions for appropriate bioimage storage, data handling, data analysis, data publication, and to provide overarching standards and support for bioimage data management for the scientific community. Our final goal is to enable researchers to make their bioimaging data Findable, Accessible, Interoperable, and Reusable (FAIR).\n\nIf you need help or advise on how to handle your bioimaging data, NFDI4BIOIMAGE Data Stewards are here to provide support. Beginning of 2024 we have set up a Help Desk to get in contact with our Data Steward team. You can use the help request form (https://nfdi4bioimage.de/help-desk/) or write an e-mail to helpdesk@nfdi4bioimage.de.\nFor further information you can also get in contact with our project office via e-mail (office@nfdi4bioimage.de) or visit our webpage https://nfdi4bioimage.de.",
      "funder": [],
      "identifier": "S-BIAD2269",
      "keywords": [
        "NFDI4BIOIMAGE"
      ],
      "license": "https://creativecommons.org/licenses/by/4.0/",
      "name": "NFDI4BIOIMAGE Calendar 2025",
      "publisher": {
        "@id": "https://www.ebi.ac.uk/bioimage-archive/"
      },
      "size": [
        {
          "@id": "#480bb0bc-db43-46e5-88ae-071380b9d63c"
        },
        {
          "@id": "#1037e7dd-b10a-47a1-885c-1f3b2998ff1c"
        }
      ],
      "thumbnailUrl": []
    },
    {
      "@id": "#7ade1c84-0681-44ef-8c91-be9d0c6ffea5",
      "@type": [
        "Person"
      ],
      "affiliation": [
        {
          "@id": "#a26bd017-2390-452c-b3cf-3ee6dcd4c307"
        }
      ],
      "email": "w.zuschratter@t-online.de",
      "name": "Heidi Faber-Zuschratter"
    },
    {
      "@id": "#a94f0486-8903-40bf-8d71-f772285003b5",
      "@type": [
        "Person"
      ],
      "affiliation": [
        {
          "@id": "#d78559c0-f752-4a28-bda2-fbbdfb260c49"
        }
      ],
      "email": "markus.wilke@ovgu.de",
      "name": "Markus Wilke"
    },
    {
      "@id": "#bf52a493-dfb2-489e-90b8-fcc88494e54e",
      "@type": [
        "Person"
      ],
      "affiliation": [
        {
          "@id": "#ca1c9874-c830-461f-86b8-438b529ccced"
        }
      ],
      "email": "macas@em.uni-frankfurt.de",
      "name": "Jadranka Macas"
    },
    {
      "@id": "#d254d791-cd79-4da9-98dc-a91c15a28d18",
      "@type": [
        "Person"
      ],
      "affiliation": [
        {
          "@id": "#37273bda-df45-40c1-9c9d-a054f22e1f44"
        }
      ],
      "email": "torsten.stoeter@isg.cs.ovgu.de",
      "name": "Torsten Stöter"
    },
    {
      "@id": "#edb39b9b-aa8f-4a56-ab9b-6202aa2c9066",
      "@type": [
        "Person"
      ],
      "affiliation": [
        {
          "@id": "#b7a2032b-681d-4fdf-94a7-c3094db7e728"
        }
      ],
      "email": "d.keitel@dkfz.de",
      "name": "Denise Keitel"
    },
    {
      "@id": "https://orcid.org/0000-0001-5160-6342",
      "@type": [
        "Person"
      ],
      "affiliation": [
        {
          "@id": "#e47f2986-abc3-4733-bb7e-07723ee0a5b5"
        }
      ],
      "email": "Kira.Muentjes@uni-duesseldorf.de",
      "name": "Kira Müntjes"
    },
    {
      "@id": "https://orcid.org/0000-0001-5805-5774",
      "@type": [
        "Person"
      ],
      "affiliation": [
        {
          "@id": "#b7a2032b-681d-4fdf-94a7-c3094db7e728"
        }
      ],
      "email": "michele.bortolomeazzi@dkfz-heidelberg.de",
      "name": "Michele Bortolomeazzi"
    },
    {
      "@id": "https://orcid.org/0000-0001-7411-9299",
      "@type": [
        "Person"
      ],
      "affiliation": [
        {
          "@id": "#438a2894-716d-4d6f-8868-70f35898a165"
        }
      ],
      "email": "sander.bekeschus@inp-greifswald.de",
      "name": "Sander Bekeschus"
    },
    {
      "@id": "https://orcid.org/0000-0001-9301-3211",
      "@type": [
        "Person"
      ],
      "affiliation": [
        {
          "@id": "#b7a2032b-681d-4fdf-94a7-c3094db7e728"
        }
      ],
      "email": "pooja.sant@dkfz-heidelberg.de",
      "name": "Pooja Sant"
    },
    {
      "@id": "https://orcid.org/0000-0001-9309-7531",
      "@type": [
        "Person"
      ],
      "affiliation": [
        {
          "@id": "#927bd72e-a2ff-4ab8-88bd-55d81a57ee06"
        }
      ],
      "email": "claire.chalopin@hawk.de",
      "name": "Claire Chalopin"
    },
    {
      "@id": "https://orcid.org/0000-0001-9951-9395",
      "@type": [
        "Person"
      ],
      "affiliation": [
        {
          "@id": "#6c3d02db-625b-4f9e-ab9d-9a0859d8ce3b"
        }
      ],
      "email": "karsten.rippe@dkfz-heidelberg.de",
      "name": "Karsten Rippe"
    },
    {
      "@id": "https://orcid.org/0000-0002-1438-4389",
      "@type": [
        "Person"
      ],
      "affiliation": [
        {
          "@id": "#b7a2032b-681d-4fdf-94a7-c3094db7e728"
        }
      ],
      "email": "alikhuseyno@gmail.com",
      "name": "Alik Huseynov"
    },
    {
      "@id": "https://orcid.org/0000-0002-3409-2340",
      "@type": [
        "Person"
      ],
      "affiliation": [
        {
          "@id": "#3ac82d15-b041-4a97-884c-ed8431df650e"
        }
      ],
      "email": "k.okonechnikov@kitz-heidelberg.de",
      "name": "Konstantin Okonechnikov"
    },
    {
      "@id": "https://orcid.org/0000-0002-3562-6121",
      "@type": [
        "Person"
      ],
      "affiliation": [
        {
          "@id": "#8a7e5d6b-cffb-4a5a-a391-8d26106c602a"
        }
      ],
      "email": "k.pajtler@kitz-heidelberg.de",
      "name": "Kristian W. Pajtler"
    },
    {
      "@id": "https://orcid.org/0000-0002-3706-7458",
      "@type": [
        "Person"
      ],
      "affiliation": [
        {
          "@id": "#23cedd80-2e33-4f76-ac43-d37d1c9d3edb"
        }
      ],
      "email": "roland.hartig@med.ovgu.de",
      "name": "Roland Hartig"
    },
    {
      "@id": "https://orcid.org/0000-0002-3844-9933",
      "@type": [
        "Person"
      ],
      "affiliation": [
        {
          "@id": "#8a7e5d6b-cffb-4a5a-a391-8d26106c602a"
        }
      ],
      "email": "d.ghasemi@kitz-heidelberg.de",
      "name": "David R. Ghasemi"
    },
    {
      "@id": "https://orcid.org/0000-0002-5782-9085",
      "@type": [
        "Person"
      ],
      "affiliation": [
        {
          "@id": "#e47f2986-abc3-4733-bb7e-07723ee0a5b5"
        }
      ],
      "email": "Kerstin.Schipper@hhu.de",
      "name": "Kerstin Schipper"
    },
    {
      "@id": "https://orcid.org/0000-0002-6209-2364",
      "@type": [
        "Person"
      ],
      "affiliation": [
        {
          "@id": "#5662987e-12b6-484c-8538-e761425d46f1"
        }
      ],
      "email": "michael.schlierf@tu-dresden.de",
      "name": "Michael Schlierf"
    },
    {
      "@id": "https://orcid.org/0000-0002-6300-5541",
      "@type": [
        "Person"
      ],
      "affiliation": [
        {
          "@id": "#baa519c0-5171-4562-a0c6-df7fd4ca338e"
        }
      ],
      "email": "thorsten.mascher@tu-dresden.de",
      "name": "Thorsten Mascher"
    },
    {
      "@id": "https://orcid.org/0000-0002-7059-4030",
      "@type": [
        "Person"
      ],
      "affiliation": [
        {
          "@id": "#b7a2032b-681d-4fdf-94a7-c3094db7e728"
        }
      ],
      "email": "j.mallm@dkfz-heidelberg.de",
      "name": "Jan-Philipp Mallm"
    },
    {
      "@id": "https://orcid.org/0000-0002-7122-2343",
      "@type": [
        "Person"
      ],
      "affiliation": [
        {
          "@id": "#41995e20-88b9-4fbb-b66d-7cc616a08f47"
        }
      ],
      "email": "m.zurowietz@uni-bielefeld.de",
      "name": "Martin Zurowietz"
    },
    {
      "@id": "https://orcid.org/0000-0002-7986-1158",
      "@type": [
        "Person"
      ],
      "affiliation": [
        {
          "@id": "#41995e20-88b9-4fbb-b66d-7cc616a08f47"
        }
      ],
      "email": "tim.nattkemper@uni-bielefeld.de",
      "name": "Tim W. Nattkemper"
    },
    {
      "@id": "https://orcid.org/0000-0002-8773-8862",
      "@type": [
        "Person"
      ],
      "affiliation": [
        {
          "@id": "#438a2894-716d-4d6f-8868-70f35898a165"
        }
      ],
      "email": "lea.miebach@inp-greifswald.de",
      "name": "Lea Miebach"
    },
    {
      "@id": "https://orcid.org/0000-0002-9845-6393",
      "@type": [
        "Person"
      ],
      "affiliation": [
        {
          "@id": "#a26bd017-2390-452c-b3cf-3ee6dcd4c307"
        }
      ],
      "email": "w.zuschratter@t-online.de",
      "name": "Werner Zuschratter"
    },
    {
      "@id": "https://orcid.org/0000-0003-0536-835X",
      "@type": [
        "Person"
      ],
      "affiliation": [
        {
          "@id": "#e9f90bc5-80dc-4abd-ab26-f8a283d1f673"
        }
      ],
      "email": "lueck@ipk-gatersleben.de",
      "name": "Stefanie Lück"
    },
    {
      "@id": "https://orcid.org/0000-0003-1717-3138",
      "@type": [
        "Person"
      ],
      "affiliation": [
        {
          "@id": "#b522c21a-87f1-4dd4-a63c-f319c7aa75f0"
        },
        {
          "@id": "#d29af429-b7f4-4e02-9ee3-26aee261890e"
        }
      ],
      "email": "Ksenia.Krooss@hhu.de",
      "name": "Ksenia Krooß"
    },
    {
      "@id": "https://orcid.org/0000-0003-2292-9286",
      "@type": [
        "Person"
      ],
      "affiliation": [
        {
          "@id": "#6c3d02db-625b-4f9e-ab9d-9a0859d8ce3b"
        }
      ],
      "email": "S.Schumacher@dkfz-heidelberg.de",
      "name": "Sabrina Schumacher"
    },
    {
      "@id": "https://orcid.org/0000-0003-3054-3121",
      "@type": [
        "Person"
      ],
      "affiliation": [
        {
          "@id": "#6c3d02db-625b-4f9e-ab9d-9a0859d8ce3b"
        }
      ],
      "email": "a.rademacher@dkfz-heidelberg.de",
      "name": "Anne Rademacher"
    },
    {
      "@id": "https://orcid.org/0009-0000-0645-6891",
      "@type": [
        "Person"
      ],
      "affiliation": [
        {
          "@id": "#cacc2d2b-5144-47ac-a2fa-1447060ea37f"
        }
      ],
      "email": "viros101@uni-duesseldorf.de",
      "name": "Vivien Joisten-Rosenthal"
    },
    {
      "@id": "https://orcid.org/0009-0000-1254-7431",
      "@type": [
        "Person"
      ],
      "affiliation": [
        {
          "@id": "#6c3d02db-625b-4f9e-ab9d-9a0859d8ce3b"
        }
      ],
      "email": "sinajasmin.wille@dkfz-heidelberg.de",
      "name": "Sina Jasmin Wille"
    },
    {
      "@id": "https://orcid.org/0009-0001-9020-1169",
      "@type": [
        "Person"
      ],
      "affiliation": [
        {
          "@id": "#927bd72e-a2ff-4ab8-88bd-55d81a57ee06"
        }
      ],
      "email": "haowen.jiang@hawk.de",
      "name": "Haowen Jiang"
    },
    {
      "@id": "https://orcid.org/0009-0002-1414-3291",
      "@type": [
        "Person"
      ],
      "affiliation": [
        {
          "@id": "#c2aa54d2-cc74-4730-9f8b-3bc09646abe6"
        }
      ],
      "email": "schwarz@evolbio.mpg.de",
      "name": "Michael Schwarz"
    },
    {
      "@id": "https://orcid.org/0009-0002-4195-2406",
      "@type": [
        "Person"
      ],
      "affiliation": [
        {
          "@id": "#94b00245-18b5-4f29-a73b-4f3dbe3f3aad"
        }
      ],
      "email": "k.warstat@fz-juelich.de",
      "name": "Kevin Warstat"
    },
    {
      "@id": "https://orcid.org/0009-0004-6533-7410",
      "@type": [
        "Person"
      ],
      "affiliation": [
        {
          "@id": "#baa519c0-5171-4562-a0c6-df7fd4ca338e"
        }
      ],
      "email": "denis.iliasov@tu-dresden.de",
      "name": "Denis Iliasov"
    },
    {
      "@id": "https://orcid.org/0009-0009-2532-9121",
      "@type": [
        "Person"
      ],
      "affiliation": [
        {
          "@id": "#5662987e-12b6-484c-8538-e761425d46f1"
        }
      ],
      "email": "pilar.loerzing@tu-dresden.de",
      "name": "Pilar Lörzing"
    },
    {
      "@id": "#23cedd80-2e33-4f76-ac43-d37d1c9d3edb",
      "@type": [
        "Organization"
      ],
      "name": "Institute for Molecular and Clinical Immunology and Service Unit Multiparametric Bioimaging and Cytometry, University of Magdeburg, Germany"
    },
    {
      "@id": "#37273bda-df45-40c1-9c9d-a054f22e1f44",
      "@type": [
        "Organization"
      ],
      "name": "Combinatorial NeuroImaging Core Facility, Leibniz Institute for Neurobiology, Magdeburg, Germany"
    },
    {
      "@id": "#3ac82d15-b041-4a97-884c-ed8431df650e",
      "@type": [
        "Organization"
      ],
      "name": "Hopp-Children’s Cancer Center Heidelberg (KiTZ), Heidelberg, Germany. Division of Pediatric Neuro-oncology, German Cancer Consortium (DKTK), German Cancer Research Center (DKFZ), Heidelberg, Germany"
    },
    {
      "@id": "#41995e20-88b9-4fbb-b66d-7cc616a08f47",
      "@type": [
        "Organization"
      ],
      "name": "Biodata Mining Group, Faculty of Technology, University of Bielefeld, Germany"
    },
    {
      "@id": "#438a2894-716d-4d6f-8868-70f35898a165",
      "@type": [
        "Organization"
      ],
      "name": "ZIK Plasmatis, Leibniz Institute for Plasma Science and Technology, Greifswald, Germany"
    },
    {
      "@id": "#5662987e-12b6-484c-8538-e761425d46f1",
      "@type": [
        "Organization"
      ],
      "name": "Molecular Biophysics, B CUBE - Center for Molecular and Cellular Bioengineering, Technical University Dresden, Germany"
    },
    {
      "@id": "#6c3d02db-625b-4f9e-ab9d-9a0859d8ce3b",
      "@type": [
        "Organization"
      ],
      "name": "Division of Chromatin Networks, German Cancer Research Center (DKFZ) and Bioquant, Heidelberg, Germany"
    },
    {
      "@id": "#8a7e5d6b-cffb-4a5a-a391-8d26106c602a",
      "@type": [
        "Organization"
      ],
      "name": "Hopp-Children’s Cancer Center Heidelberg (KiTZ), Heidelberg, Germany. Division of Pediatric Neuro-oncology, German Cancer Consortium (DKTK), German Cancer Research Center (DKFZ), Heidelberg, Germany. Department of Pediatric Oncology, Hematology, and Immunology, Heidelberg University Hospital; Heidelberg; Germany"
    },
    {
      "@id": "#927bd72e-a2ff-4ab8-88bd-55d81a57ee06",
      "@type": [
        "Organization"
      ],
      "name": "Data-Driven Imaging in Medicine, University of Applied Sciences and Arts, Göttingen, Germany"
    },
    {
      "@id": "#94b00245-18b5-4f29-a73b-4f3dbe3f3aad",
      "@type": [
        "Organization"
      ],
      "name": "Plant Sciences, Institute of Bio- und Geosciences, Forschungszentrum Jülich, Germany"
    },
    {
      "@id": "#a26bd017-2390-452c-b3cf-3ee6dcd4c307",
      "@type": [
        "Organization"
      ],
      "name": "Leibniz Institute for Neurobiology, Magdeburg, Germany"
    },
    {
      "@id": "#b522c21a-87f1-4dd4-a63c-f319c7aa75f0",
      "@type": [
        "Organization"
      ],
      "name": "Center for Advanced Imaging, Heinrich Heine University Düsseldorf, Germany"
    },
    {
      "@id": "#b7a2032b-681d-4fdf-94a7-c3094db7e728",
      "@type": [
        "Organization"
      ],
      "name": "Single-cell Open Lab, German Cancer Research Center (DKFZ), Heidelberg, Germany"
    },
    {
      "@id": "#baa519c0-5171-4562-a0c6-df7fd4ca338e",
      "@type": [
        "Organization"
      ],
      "name": "General Microbiology, Technical University Dresden, Germany"
    },
    {
      "@id": "#c2aa54d2-cc74-4730-9f8b-3bc09646abe6",
      "@type": [
        "Organization"
      ],
      "name": "Department Microbial Population Biology, Max-Planck Institute for Evolutionary Biology, Ploen, Germany"
    },
    {
      "@id": "#ca1c9874-c830-461f-86b8-438b529ccced",
      "@type": [
        "Organization"
      ],
      "name": "Institute of Neurology (Edinger Institute), University Hospital, Goethe University, Frankfurt, Germany"
    },
    {
      "@id": "#cacc2d2b-5144-47ac-a2fa-1447060ea37f",
      "@type": [
        "Organization"
      ],
      "name": "Institute for Biological Data Science, Heinrich Heine University Düsseldorf, Germany"
    },
    {
      "@id": "#d29af429-b7f4-4e02-9ee3-26aee261890e",
      "@type": [
        "Organization"
      ],
      "name": "NFDI4BIOIMAGE"
    },
    {
      "@id": "#d78559c0-f752-4a28-bda2-fbbdfb260c49",
      "@type": [
        "Organization"
      ],
      "name": "Institute of Materials, Technologies and Mechanics, University of Magdeburg, Germany"
    },
    {
      "@id": "#e47f2986-abc3-4733-bb7e-07723ee0a5b5",
      "@type": [
        "Organization"
      ],
      "name": "Institute of Microbiology, Heinrich Heine University Düsseldorf, Germany"
    },
    {
      "@id": "#e9f90bc5-80dc-4abd-ab26-f8a283d1f673",
      "@type": [
        "Organization"
      ],
      "name": "Department of Breeding Research, Leibniz Institute of Plant Genetics and Crop Plant Research, Gatersleben, Germany"
    },
    {
      "@id": "https://www.ebi.ac.uk/bioimage-archive/",
      "@type": [
        "Organization"
      ],
      "name": "BioImage Archive"
    },
    {
      "@id": "https://doi.org/10.1101/2024.07.04.602038",
      "@type": [
        "ScholarlyArticle"
      ],
      "datePublished": "2024",
      "name": "Glioma-associated tertiary lymphoid structures are sites of lymphocyte clonal expansion and plasma cell formation"
    },
    {
      "@id": "https://doi.org/10.1186/s12983-022-00478-5",
      "@type": [
        "ScholarlyArticle"
      ],
      "datePublished": "2023",
      "name": "A pilot study to estimate the population size of endangered Galápagos marine iguanas using drones."
    },
    {
      "@id": "https://doi.org/10.1186/s13059-025-03624-4",
      "@type": [
        "ScholarlyArticle"
      ],
      "datePublished": "2025",
      "name": "Comparison of spatial transcriptomics technologies using tumor cryosections."
    },
    {
      "@id": "https://doi.org/10.3389/fmars.2017.00083",
      "@type": [
        "ScholarlyArticle"
      ],
      "datePublished": "2017",
      "name": "BIIGLE 2.0 - Browsing and Annotating Large Marine Image Collections"
    },
    {
      "@id": "https://doi.org/10.3389/fmars.2021.760036",
      "@type": [
        "ScholarlyArticle"
      ],
      "datePublished": "2021",
      "name": "Current Trends and Future Directions of Large Scale Image and Video Annotation: Observations From Four Years of BIIGLE 2.0"
    },
    {
      "@id": "https://doi.org/10.5281/zenodo.15421751",
      "@type": [
        "ScholarlyArticle"
      ],
      "datePublished": "2025",
      "name": "BIIGLE"
    },
    {
      "@id": "obo:NCBITaxon_4513",
      "@type": [
        "Taxon"
      ],
      "scientificName": "Hordeum vulgare"
    },
    {
      "@id": "obo:NCBITaxon_4577",
      "@type": [
        "Taxon"
      ],
      "scientificName": "Zea mays"
    },
    {
      "@id": "obo:NCBITaxon_51208",
      "@type": [
        "Taxon"
      ],
      "scientificName": "Amblyrhynchus cristatus"
    },
    {
      "@id": "obo:NCBITaxon_5270",
      "@type": [
        "Taxon"
      ],
      "scientificName": "Mycosarcoma maydis"
    },
    {
      "@id": "obo:NCBITaxon_78475",
      "@type": [
        "Taxon"
      ],
      "scientificName": "Peltigera neckeri"
    },
    {
      "@id": "obo:NCBITaxon_9606",
      "@type": [
        "Taxon"
      ],
      "scientificName": "Homo sapiens"
    },
    {
      "@id": "#0901deee-337e-4c2b-b8d1-86c313ab4dd0",
      "@type": [
        "BioSample"
      ],
      "description": "Whole foliose cyanolichen thallus\nMycobiont: Peltigera\nPhotobiont: Nostoc. As part of the MibiNet SFB 1535 project (https://www.sfb1535.hhu.de), this lichen was collected in the Northern Eifel region, between Blankenheim and Schmidtheim in Germany. Lichens are among the most successful examples of complex mutualistic symbiosis, where a fungus (mycobiont) forms an association with one or more photosynthetic organisms (photobionts), including green algae and/or cyanobacteria. Based on ITS analysis, the lichen shown has been identified as Peltigera neckeri. Lichens of the genus Peltigera are classified as cyanolichens due to their symbiotic association with a cyanobacterial photobiont of the genus Nostoc. The image shows the lichen's blue-gray thallus when wet, after its collection on a mossy stone.",
      "name": "October Image 2025 Biosample",
      "taxonomicRange": {
        "@id": "obo:NCBITaxon_78475"
      }
    },
    {
      "@id": "#09e42620-efac-40fe-9371-ea1ab09d4565",
      "@type": [
        "BioSample"
      ],
      "description": ".. This image shows the BIIGLE image and video annotation tool, which is a web-based software for collaborative research on large imaging datasets [1, 2]. It offers tools for manual and computer-assisted annotation, quality control and the collaboration on custom taxonomies to describe objects. BIIGLE is freely available and can be installed in cloud environments, a local network or on mobile platforms during research expeditions. A public instance can be found at biigle.de.\nThe annotated image shows the coastline of Fernandina Island, Galapagos, which is the habitat of the Galapagos Marine Iguana (Amblyrhynchus cristatus). The image is a large mosaic that was stitched together from many individual images captured by a drone. The green annotations marking the iguanas were machine-generated as part of a feasibility study for the automatic analysis of the data in the project Iguanas from Above [3, 4].\n\n[1] Langenkämper, D., Zurowietz, M., Schoening, T., & Nattkemper, T. W. (2017). BIIGLE 2.0-browsing and annotating large marine image collections. Frontiers in Marine Science, 4, 83. https://doi.org/10.3389/fmars.2017.00083\n[2] Zurowietz, M., & Nattkemper, T. W. (2021). Current trends and future directions of large scale image and video annotation: Observations from four years of BIIGLE 2.0. Frontiers in Marine Science, 8, 760036. https://doi.org/10.3389/fmars.2021.760036\n[3] Varela-Jaramillo, A., Rivas-Torres, G., Guayasamin, J. M., Steinfartz, S., & MacLeod, A. (2023). A pilot study to estimate the population size of endangered Galápagos marine iguanas using drones. Frontiers in Zoology, 20(1), 4. https://doi.org/10.1186/s12983-022-00478-5\n[4] https://iguanasfromabove.com",
      "name": "April Image 2025 Biosample",
      "taxonomicRange": {
        "@id": "obo:NCBITaxon_51208"
      }
    },
    {
      "@id": "#0f4d703f-0712-4c78-9626-a1746c9fc973",
      "@type": [
        "BioSample"
      ],
      "description": "Bacteria. The image shows 125x magnified microscopic details of a biofilm formed by Pseudomonas fluorescence on the surface of a liquid culture medium. The culture was inoculated with a cellulose-overexpressing and surface-colonizing mScarlet-tagged wild type and a GFP-tagged mutant that is unable to colonize the surface. The biofilm can collapse over time due to its own mass, so that new strategies have to be developed and thus a life cycle emerges.",
      "name": "March Image 2025 Biosample",
      "taxonomicRange": []
    },
    {
      "@id": "#16412a93-a529-40c5-8a4d-2d9917224f17",
      "@type": [
        "BioSample"
      ],
      "description": ".. PhenoRob (EXC 2070) - Crop Spectra\nThis illustration compares two orthomosaics generated from UAV imagery. On the left, a true-color RGB orthomosaic is displayed, accompanied by three smaller orthomosaic images above it, each representing the red, green, and blue bands, vividly colored to highlight their significance. On the right, a corresponding NDVI orthomosaic of the same field is shown, with two images above it illustrating the red and near-infrared bands used as input. All images are processed products from structure from motion modelling.",
      "name": "June Image 2025 Biosample",
      "taxonomicRange": {
        "@id": "obo:NCBITaxon_4577"
      }
    },
    {
      "@id": "#2e202e92-1a87-4d67-8f74-de79ddce334a",
      "@type": [
        "BioSample"
      ],
      "description": "Leaves of cultivar Golden promise. Analysis of Hordeum vulgare cv. Golden promise infected with Blumeria graminis f. sp. hordei (causative for barley powdery mildew). To study the interaction between Hordeum vulgare and Blumeria graminis f. sp. hordei advanced imaging techniques and automated image analysis were used. The study involves imaging followed by automated segmentation and CNN-based prediction of fungal structures.\nThis microscopy image shows the interaction between barley (cv. Golden Promise) and the barley powdery mildew fungus (Blumeria graminis f.sp. hordei), 48 hours post-inoculation. Fungal structures were stained with Coomassie dye and scanned using a Zeiss Axio Scan Z.1 microscope with a 5x objective. The top section shows segmented hyphal colonies (black) against the plant tissue (white), while the bottom displays a machine-learning analysis using a convolutional neural network to predict fungal structures. The red bounding boxes show the outer boundaries of detected objects, while the green contours precisely trace the segmented hyphae. The analysis was done with BluVision Micro software (https://github.com/snowformatics/BluVisionMicro).",
      "name": "May Image 2025 Biosample",
      "taxonomicRange": {
        "@id": "obo:NCBITaxon_4513"
      }
    },
    {
      "@id": "#435ebc27-6a1c-46d1-a604-e0bdc02eed2c",
      "@type": [
        "BioSample"
      ],
      "description": ".. Research project within DFG CRC 854 (Molecular organisation of cellular communication within the immune system). Ultrastructure of the immune synapse.\nThe scanning electron micrograph shows the approach of T-lymphocytes (Jurkat cells; cyan) to an antigen-presenting B cell (Raji cell; yellow) in the center. The image was taken as part of the research work of the CRC 854, which focused on molecular processes that regulate inter- and intracellular communication within the immune system.",
      "name": "September Image 2025 Biosample",
      "taxonomicRange": {
        "@id": "obo:NCBITaxon_9606"
      }
    },
    {
      "@id": "#53a56d78-8a97-4a32-991d-4e34598853c5",
      "@type": [
        "BioSample"
      ],
      "description": "Hyphae. Characterization of the intrinsic autofluorescence in filamentous actinobacteria.\nThe sample was provided through a collaboration with the group of Thorsten Mascher at TU Dresden. Aim of this project is to explore the cellular autofluorescence patterns in Streptomyces using advanced imaging techniques. Streptomyces coelicolor are multicellular, mycelial bacteria that grow as vegetative hyphae. The use of confocal microscopy in this project was crucial for optically sectioning these filamentous cells, enabling the resolution of their cellular autofluorescence patterns with a high signal-to-noise ratio, which allowed us to visualize the 3D arrangement of the hyphae.",
      "name": "July Image 2025 Biosample",
      "taxonomicRange": []
    },
    {
      "@id": "#82d54a62-228d-4777-9c03-edb252ae232d",
      "@type": [
        "BioSample"
      ],
      "description": "Hand. Quantification of tissue reperfusion using real-time spectral imaging and deep learning.\nThis image illustrates tissue oxygen saturation in the hand, calculated using various computer-assisted methods and based on hyperspectral and multispectral imaging. The purpose of this image is to compare the perfusion parameters (3 and 4) obtained with multispectral cameras delivering relatively less spectral information but capable of real-time imaging against the perfusion parameters (2) obtained with a hyperspectral medical system delivering large spectral information but not capable of real-time imaging. The picture shows that deep learning methods (4) perform better than classical methods (3) that are not based on artificial intelligence. It lays the groundwork for future real-time quantitative assessment of perfusion during organ transplantation surgeries.",
      "name": "August Image 2025 Biosample",
      "taxonomicRange": {
        "@id": "obo:NCBITaxon_9606"
      }
    },
    {
      "@id": "#b87a756e-1614-42ca-ac3c-b9fec3827151",
      "@type": [
        "BioSample"
      ],
      "description": "Bone marrow-mesenchymal stem cells (BM-MSCs). A Heart for Redox Biology: The image of primary bone mesenchymal stromal/stem cells (hBM-MSCs) was captured in a study evaluating the cellular effects of therapeutic oxidation in the context of regenerative medicine. The cells were isolated from an arthroplasty patient cohort in a joint research project between the Center for Orthopaedics at University Medical Center and the group ZIK plasmatis at the Leibniz Institute for Plasma Science and Technology (INP) in Greifswald. You can appreciate the characteristic morphology and complex actin cytoskeleton that is crucial for the cellular function of hBM-MSCs. Can you spot the heart that is formed by the prominent actin protrusions of interconnected cells?",
      "name": "January Image 2025 Biosample",
      "taxonomicRange": {
        "@id": "obo:NCBITaxon_9606"
      }
    },
    {
      "@id": "#dc1955f8-e10f-4573-9c9f-2c174168663c",
      "@type": [
        "BioSample"
      ],
      "description": ".. Comparison of spatial transcriptomics technologies for medulloblastoma cryosection.\nThe image is a visualization showing the integration of multimodal data including a spinning disk confocal image and gene expression data from a spatial transcriptomic experiment on a human medulloblastoma sample. The microscopy image of the tissue with the nuclei in white has been overlayed with the result of the cell segmentation colored according to the assigned cell type (immune cells: red, stromal cells: violet, brain cells: cyan/blue, tumor cells: green). A subset of transcripts for three genes whose expression varies across the different cell types in the tissue have been represented as colored dots (CD4 (immune cells): red, PTCH1 (tumor cells): green, AQP4 (brain cells): blue).",
      "name": "Cover Image 2025 Biosample",
      "taxonomicRange": {
        "@id": "obo:NCBITaxon_9606"
      }
    },
    {
      "@id": "#f500750a-7c33-4ade-9d40-acb6a342c44f",
      "@type": [
        "BioSample"
      ],
      "description": ".. Immunomonitoring study in human oncology.\nThe image shows a perivascular accumulation of B cells, T cells and plasma cells in a human brain tumor. These structures, also known as tertiary lymphoid structures, are sites of lymphocyte clonal expansion and plasma cell formation. The study aims to determine the clinical relevance and immunological function of tertiary lymphoid structures in human primary brain tumors.",
      "name": "November Image 2025 Biosample",
      "taxonomicRange": {
        "@id": "obo:NCBITaxon_9606"
      }
    },
    {
      "@id": "#fa56d995-c1ba-4bfc-99f4-b1c9d120ca74",
      "@type": [
        "BioSample"
      ],
      "description": ".. Visualisation of microbial oil in the fungus Ustilago maydis.\nThe microscopic image shows yeast cells of the fungal model Ustilago maydis that produce single cell oil at nitrogen-starvation conditions. The genetically engineered cells are packed with oil droplets that were visualized by BODIPY staining. The study was conducted in the framework of the BioSC project \"NextVegOil\".",
      "name": "December Image 2025 Biosample",
      "taxonomicRange": {
        "@id": "obo:NCBITaxon_5270"
      }
    },
    {
      "@id": "#0f8c3557-01a7-4dce-95ea-02df11ef2759",
      "@type": [
        "LabProtocol"
      ],
      "description": "Fluorescence\nChannel 1 – content: DAPI; Channel 1 – biological entity: Nuclei (DNA)\nImages were recorded at 16-bit depth and with 1024x1024 pixels dimensions (pixel size: 0.217 µm) using an iXon Ultra 888 EM-CCD camera. The region of interest was selected based on the DAPI signal and 50 z-slices were acquired with a step size of 0.4 µm (20 µm z-range) per field of view (FOV). Tiles were imaged with a 10% overlap to ensure accurate stitching.\nSize description: 8800x8788+0+0 pixels (Primary image)\nPixel/voxel size description: 0.217 µm (Primary image)\nChannel information: RGB\nTiles were imaged with a 10% overlap to ensure accurate stitching. Subsequently, a flatfield-correction was conducted based on the DAPI channel and stitching and registration of the tiles was conducted with Fiji. First, SDCM image stacks were subjected to a maximum intensity projection, followed by flat field and chromatic aberration correction using a custom script. Next, image tiles were stitched using the “Grid/Collection Stitching” plugin. DAPI images from SDCM were registered to MC or Xenium widefield images using “Register Virtual Stack Slices” with Affine feature extraction model and the Elastic bUnwarpJ splines registration model. In case of further staining, images were transformed via Transform Virtual Stack slices employing the transformation file of the DAPI registration.",
      "labEquipment": "Imaging of RNAscope samples and reimaging of Xenium slides by SDCM was conducted on an Andor Dragonfly 505 spinning disk confocal system equipped with a Nikon Ti2-E inverted microscope and a CFI P-Fluor 40X/1.30 oil objective or a Plan Apo 60x/1.40 oil objective. Multicolor images were acquired with the following laser lines 405 nm (DAPI), 488 nm (Alexa 488, eosin), 561 nm (Atto 550), 637 nm (Atto 647) 730nm (Alexa 750).",
      "measurementTechnique": [],
      "name": "Cover Image 2025 Image Acquisition"
    },
    {
      "@id": "#1af24027-4b94-438d-bc58-e50b181850da",
      "@type": [
        "LabProtocol"
      ],
      "description": "26,545 × 20,894 px",
      "labEquipment": "DJI Mavic 2 Pro with Hasselblad L1D-20c",
      "measurementTechnique": [],
      "name": "April Image 2025 Image Acquisition"
    },
    {
      "@id": "#4c2bd05d-fff9-4056-8e7b-165168a9c58b",
      "@type": [
        "LabProtocol"
      ],
      "description": "(1) RGB image of the hand under normal perfusion.\n(2) Perfusion parameter map computed based on hyperspectral imaging (100 spectral bands between 500 and 1000 nm). High perfusion values are represented in red, low perfusion values in blue.\n(3) Perfusion parameter map computed based on multispectral imaging (31 spectral bands between 460 and 850 nm) and using the spectral bands that are available but that are less than in (2). Therefore, the result in (3) looks very different from the result in (2).\n(4) Perfusion parameter map computed based on multispectral imaging and using a deep neural network. The result in (4) looks similar to the result in (2).\nImage resolution hyperspectral imaging: Spatial Resolution: 480*640 pixels; Spectral Resolution: 500 nm-1000 nm, 100 bands, 5 nm.\nImage resolution multispectral imaging: Spatial Resolution: 1088*2048 pixels; Spectral Resolution: 16 bands in 460-600 nm; 15 bands in 600-850 nm.\nImage mode: Reflectance",
      "labEquipment": "n/a",
      "measurementTechnique": [],
      "name": "August Image 2025 Image Acquisition"
    },
    {
      "@id": "#4e1ef450-863d-4cd6-a14a-f513bc9bb5ed",
      "@type": [
        "LabProtocol"
      ],
      "description": "HORIZON™ Viewer (Lunaphore Technologies, SA)\nChannel 1 - content: Alexa Fluor Plus 555, red; Channel 1 - biological entity: CD20 - B-cells\nChannel 2 - content: Alexa Fluor Plus 647, green; Channel 2 - biological entity: CD3 - T-cells\nChannel 3 - content: Alexa Fluor Plus 555, white; Channel 3 - biological entity: CD163 - anti-inflammatory macrophages (M2-like)\nChannel 4 - content: Alexa Fluor Plus 647, magenta; Channel 4 - biological entity: MZB-1 - Marginal zone B and B1 cell-specific protein, MEDA-7 - plasma cells, memory B-cells\nChannel 5 - content: Alexa Fluor Plus 647, orange; Channel 5 - biological entity: NF- Neurofilament - intermediate filaments around the axons\nChannel 6- content: Alexa Fluor Plus 555, cyan; Channel 6 - biological entity: GAP43 - Neuromodulin, neuronal growth-associated protein 43 - neurons\nChannel 7 - content: Alexa Fluor Plus 555, blue; Channel 7 - biological entity: vWF - von-Willebrand-Factor - endothelial cells\nPixel size: 0.23 µm/pixel\nImage size: Width 11986 pixels - 2.76 mm; Height 11514 pixels - 2.65 mm\nPixel bit depth: 16-bit\nChannel information: Displayed are 7 markers out of the highplex IF-panel; number of channels 43 (including autofluorescence)",
      "labEquipment": "COMET™ highplex seq-IF staining and scanning system v.1.1.1.0 (Lunaphore Technologies, SA), operated via COMET™ acquisition software                                                                                                                                                                                 ",
      "measurementTechnique": [],
      "name": "November Image 2025 Image Acquisition"
    },
    {
      "@id": "#745d90ad-58a1-4403-869c-1bdf3ab2a936",
      "@type": [
        "LabProtocol"
      ],
      "description": "iPhone 12 back dual wide camera 4.2mm f/1.6, size 4,032 x 3,024 px",
      "labEquipment": "Apple iPhone 12",
      "measurementTechnique": [],
      "name": "October Image 2025 Image Acquisition"
    },
    {
      "@id": "#7cdea816-f5ed-4b28-bb7e-69496fa75530",
      "@type": [
        "LabProtocol"
      ],
      "description": "Objective Lens 5x",
      "labEquipment": "Zeiss Axio Scan Z.1",
      "measurementTechnique": [],
      "name": "May Image 2025 Image Acquisition"
    },
    {
      "@id": "#9577880a-4453-4b3b-aa04-d634402f7b5e",
      "@type": [
        "LabProtocol"
      ],
      "description": "On the left, true-color RGB orthomosaic with respective red, green, and blue bands.\nOn the right, Normalized Difference Vegetation Index (NDVI) orthomosaic with respective red and near-infrared bands.",
      "labEquipment": "DJI Matrice 600 Pro with Sony alpha 7 mark IV RGB and MicaSense RedEdge-MX Dual multispectral camera",
      "measurementTechnique": [],
      "name": "June Image 2025 Image Acquisition"
    },
    {
      "@id": "#ab4ad2a2-2c88-46a5-9d79-a3d0ff9b4081",
      "@type": [
        "LabProtocol"
      ],
      "description": "Relief and fluorescence\nChannel 1 - content: Relief, grey; Channel 1 - biological entity: Details of the biofilm in transmitted light\nChannel 2 - content: mScarlet, red; Channel 2 - biological entity: WT over-expressing cellulose and colonizing the surface\nChannel 3 - content: GFP, green; Channel 3 - biological entity: ∆wss mutant unable to colonize the surface\nMagnification: 125x\nObjective PlanNeoFluar Z 1.0x\nPixel size: 0.91 µm\nImage area: 2500 x 2500 µm",
      "labEquipment": "Zeiss Axio Zoom V16",
      "measurementTechnique": [],
      "name": "March Image 2025 Acquisition"
    },
    {
      "@id": "#b1655cb1-974e-4f78-b689-6cc91e1561d8",
      "@type": [
        "LabProtocol"
      ],
      "description": "Fluorescence\nChannel 1 – content: 4',6-Diamidin-2-phenylindol (DAPI; Thermo Fisher, USA), blue; Channel 1 – biological entity: Nuclei\nChannel 2 – content: MitoSpy Green (Biolegend, USA), green; Channel 2 – biological entity: Mitochondria\nChannel 3 – content: Flash Phalloidin Red (Biolegend, USA), orange; Channel 3 – biological entity: Actin.\nRaw and processed image in comparison\nMagnification: 20x air objective (NA = 0.8)\nExcitation Channel 1: 365 nm, Channel 2: 475 nm, Channel 3: 550 nm\nDetection Channel 1: 465 nm, Channel 2: 525 nm, Channel 3: 610 nm",
      "labEquipment": "Operetta CLS (PerkinElmer, USA)",
      "measurementTechnique": [],
      "name": "January Image 2025 Image Acquisition"
    },
    {
      "@id": "#c8886441-6f0a-4b76-8838-4e023355ca75",
      "@type": [
        "LabProtocol"
      ],
      "description": "Differential interference contrast and fluorescence\nChannel 1 - content: DIC; Channel 1 - biological entity: Intact yeast cells\nChannel 2 - content: BODIPY 493/503; Channel 2 - biological entity: Intracellular lipid droplets",
      "labEquipment": "Zeiss Axio Observer.Z1; Prime BSI express; solid-state laser 488 nm",
      "measurementTechnique": [],
      "name": "December Image 2025 Image Acquisition"
    },
    {
      "@id": "#da9051d5-3650-4be7-8688-f04878bd744b",
      "@type": [
        "LabProtocol"
      ],
      "description": "Imaging was performed using a Nikon Ti-E Spinning Disk microscope with 100x objective and 1.5x tube lens. Fluorescence was excited with a 488 nm laser and emission light was filtered using a dual band filter 433/530 HC. An Andor Ixon Ultra 888 EMCCD camera was used for detection.\nChannel 1 - content: Cellular autofluorescence; Channel 1 - biological entity: S. coelicolor hyphae\nZ-stacks of confocal images with 0.2 µm step size, maximum intensity projection of individual z-stacks\nDimension extents: x: 1024 y: 1024 z: 28 px\nSize description: x: 63.12 y: 63.12 z: 5.6 µm\nPixel/voxel size description: x: 86 y: 86 z: 200 nm",
      "labEquipment": "Nikon Ti-E Spinning Disk ",
      "measurementTechnique": [
        {
          "@id": "obo:FBbi_00000253"
        }
      ],
      "name": "July Image 2025 Image Acquisition"
    },
    {
      "@id": "#e7da1cca-af16-4456-b2b3-1565276c197d",
      "@type": [
        "LabProtocol"
      ],
      "description": "Detected secondary electrons\nChannel 1 - content: Jurkat cell line E6.1 (artificial color table, cyan); Channel 1 - biological entity: Surface of Jurkat cells\nChannel 2 - content: Raji B cell lymphoma cell line (artificial color table, yellow); Channel 2 - biological entity: Surface of a Raji B cell.\nParameters: 10 keV\nMagnification: 6500x\nScale bar: 2 µm",
      "labEquipment": "FEI XL30 FEG ESEM",
      "measurementTechnique": [],
      "name": "September Image 2025 Image Acquisition"
    },
    {
      "@id": "obo:FBbi_00000253",
      "@type": [
        "DefinedTerm"
      ],
      "name": "spinning disk confocal microscopy"
    },
    {
      "@id": "#1037e7dd-b10a-47a1-885c-1f3b2998ff1c",
      "@type": [
        "QuantitiveValue"
      ],
      "unitCode": "http://purl.obolibrary.org/obo/UO_0000189",
      "unitText": "file count",
      "value": 13
    },
    {
      "@id": "#480bb0bc-db43-46e5-88ae-071380b9d63c",
      "@type": [
        "QuantitiveValue"
      ],
      "unitCode": "http://purl.obolibrary.org/obo/UO_0000233",
      "unitText": "bytes",
      "value": 237398404
    }
  ]
}